pakiet_testowy/__init__.py
pakiet_testowy/dodawanie.py
zdpytpol_eight-0.0.2.dist-info/METADATA
zdpytpol_eight-0.0.2.dist-info/WHEEL
zdpytpol_eight-0.0.2.dist-info/top_level.txt
zdpytpol_eight-0.0.2.dist-info/RECORD
