Metadata-Version: 2.1
Name: zdpytpol-eight
Version: 0.0.2
Summary: some description
Home-page: UNKNOWN
Author: Ditto
License: UNKNOWN
Platform: UNKNOWN
